p10k_edit/__about__.py
p10k_edit/__init__.py
p10k_edit/__main__.py
p10k_edit-0.0.16.dist-info/METADATA
p10k_edit-0.0.16.dist-info/WHEEL
p10k_edit-0.0.16.dist-info/entry_points.txt
p10k_edit-0.0.16.dist-info/licenses/LICENSE.txt
p10k_edit-0.0.16.dist-info/RECORD
