Metadata-Version: 2.4
Name: p10k-edit
Version: 0.0.16
Summary: Tool to Edit PowerLevel10k p10k.zsh Config File (work-in-progress)
Project-URL: Documentation, https://github.com/kkatayama/p10k-edit#readme
Project-URL: Issues, https://github.com/kkatayama/p10k-edit/issues
Project-URL: Source, https://github.com/kkatayama/p10k-edit
Author-email: Teddy Katayama <kkatayama@udel.edu>
License-Expression: MIT
License-File: LICENSE.txt
Keywords: POWERLEVEL10K,p10k,p10k.zsh
Classifier: Development Status :: 4 - Beta
Classifier: Programming Language :: Python
Classifier: Programming Language :: Python :: 3.7
Classifier: Programming Language :: Python :: 3.8
Classifier: Programming Language :: Python :: 3.9
Classifier: Programming Language :: Python :: 3.10
Classifier: Programming Language :: Python :: 3.11
Classifier: Programming Language :: Python :: Implementation :: CPython
Classifier: Programming Language :: Python :: Implementation :: PyPy
Requires-Python: >=3.7
Requires-Dist: iterm2
Requires-Dist: psutil
Requires-Dist: pyobjc
Requires-Dist: rich
